{
  "type": "news",
  "slug": "arxiv-cs-ai-oai-arxiv-org-2606-25449v5",
  "name": "Reclaim Evaluation: A Lossy Memory Is Worse Than an Empty One",
  "summary": "arXiv:2606.25449v5 Announce Type: replace-cross Abstract: A language model's memory can be worse than no memory at all when the model or its interface is disposed to act on it: a memory that keeps...",
  "description": "arXiv:2606.25449v5 Announce Type: replace-cross Abstract: A language model's memory can be worse than no memory at all when the model or its interface is disposed to act on it: a memory that keeps a wrong conclusion but drops the work behind it leads a model to re-emit the stale value as a confident answer, where an empty memory leads it to abstain. We call this brittle memory. The information...",
  "tags": [
    "news",
    "arxiv-cs-ai"
  ],
  "externalLinks": [
    {
      "label": "arXiv cs.AI",
      "href": "https://arxiv.org/abs/2606.25449"
    }
  ],
  "timeline": [
    {
      "date": "2026-07-22",
      "type": "milestone",
      "title": "Published",
      "description": "Posted by arXiv cs.AI.",
      "href": "https://arxiv.org/abs/2606.25449"
    }
  ],
  "source": "arXiv cs.AI",
  "publishedAt": "2026-07-22",
  "expiryAt": "2026-08-21T00:00:00.000Z",
  "author": "Alex Kwon"
}