{
  "type": "news",
  "slug": "arxiv-cs-ai-oai-arxiv-org-2607-18272v1",
  "name": "Market Strategy Evaluation for Prosumers in Local Electricity Markets",
  "summary": "arXiv:2607.18272v1 Announce Type: cross Abstract: Prosumers equipped with distributed generation and flexible loads form autonomous cyber-physical energy systems that control local resources and pa...",
  "description": "arXiv:2607.18272v1 Announce Type: cross Abstract: Prosumers equipped with distributed generation and flexible loads form autonomous cyber-physical energy systems that control local resources and participate in local energy markets with minimal human intervention. This work develops and evaluates an agent-based simulation platform in which agents, representing prosumer households with photovolta...",
  "tags": [
    "news",
    "arxiv-cs-ai"
  ],
  "externalLinks": [
    {
      "label": "arXiv cs.AI",
      "href": "https://arxiv.org/abs/2607.18272"
    }
  ],
  "timeline": [
    {
      "date": "2026-07-22",
      "type": "milestone",
      "title": "Published",
      "description": "Posted by arXiv cs.AI.",
      "href": "https://arxiv.org/abs/2607.18272"
    }
  ],
  "source": "arXiv cs.AI",
  "publishedAt": "2026-07-22",
  "expiryAt": "2026-08-21T00:00:00.000Z",
  "author": "Lukas Peter Wagner, Raoul Bisson, Felix Gehlhoff"
}