{
  "type": "news",
  "slug": "arxiv-cs-ai-oai-arxiv-org-2607-15003v1",
  "name": "SMC-ES: Automated synthesis of formally verified control policies",
  "summary": "arXiv:2607.15003v1 Announce Type: new Abstract: The deployment of autonomous cyber-physical systems in safety-critical environments requires closed-loop control strategies (i.e., policies) that are...",
  "description": "arXiv:2607.15003v1 Announce Type: new Abstract: The deployment of autonomous cyber-physical systems in safety-critical environments requires closed-loop control strategies (i.e., policies) that are not only performant but also provably safe and robust. While learning-based methodologies such as Reinforcement Learning offer flexible and scalable approaches to automatically synthesize such contro...",
  "tags": ["news", "arxiv-cs-ai"],
  "externalLinks": [
    {
      "label": "arXiv cs.AI",
      "href": "https://arxiv.org/abs/2607.15003"
    }
  ],
  "timeline": [
    {
      "date": "2026-07-17",
      "type": "milestone",
      "title": "Published",
      "description": "Posted by arXiv cs.AI.",
      "href": "https://arxiv.org/abs/2607.15003"
    }
  ],
  "source": "arXiv cs.AI",
  "publishedAt": "2026-07-17",
  "expiryAt": "2026-08-16T00:00:00.000Z",
  "author": "Riccardo Curcio, Toni Mancini, Enrico Tronci"
}
