{
  "type": "news",
  "slug": "arxiv-cs-ai-oai-arxiv-org-2509-00761v4",
  "name": "L-MARS: Legal Multi-Agent System with Agentic Search and Citation-Faithfulness Audit",
  "summary": "arXiv:2509.00761v4 Announce Type: replace Abstract: Large language models are increasingly deployed for legal question answering, where evaluations typically focus on multiple-choice accuracy. This...",
  "description": "arXiv:2509.00761v4 Announce Type: replace Abstract: Large language models are increasingly deployed for legal question answering, where evaluations typically focus on multiple-choice accuracy. This measure overlooks a common failure: whether the citation source attached to an answer exists and supports the rule the system attributes to it. We present L-MARS, an open multi-agent legal QA system...",
  "tags": ["news", "arxiv-cs-ai"],
  "externalLinks": [
    {
      "label": "arXiv cs.AI",
      "href": "https://arxiv.org/abs/2509.00761"
    }
  ],
  "timeline": [
    {
      "date": "2026-07-17",
      "type": "milestone",
      "title": "Published",
      "description": "Posted by arXiv cs.AI.",
      "href": "https://arxiv.org/abs/2509.00761"
    }
  ],
  "source": "arXiv cs.AI",
  "publishedAt": "2026-07-17",
  "expiryAt": "2026-08-16T00:00:00.000Z",
  "author": "Boqin Yuan, Ziqi Wang"
}
