{
  "type": "news",
  "slug": "arxiv-cs-ai-oai-arxiv-org-2607-15775v1",
  "name": "AquaAugmentor: A Novel Feature Augmentation Algorithm for Water Potability Prediction",
  "summary": "arXiv:2607.15775v1 Announce Type: cross Abstract: Access to potable water is crucial for health, economic development, and sustainability. However, accurately classifying water quality remains a si...",
  "description": "arXiv:2607.15775v1 Announce Type: cross Abstract: Access to potable water is crucial for health, economic development, and sustainability. However, accurately classifying water quality remains a significant challenge due to the complexity and variability of water source data. This paper addresses the challenge of predicting water potability through machine learning and deep learning algorithms....",
  "tags": [
    "news",
    "arxiv-cs-ai"
  ],
  "externalLinks": [
    {
      "label": "arXiv cs.AI",
      "href": "https://arxiv.org/abs/2607.15775"
    }
  ],
  "timeline": [
    {
      "date": "2026-07-20",
      "type": "milestone",
      "title": "Published",
      "description": "Posted by arXiv cs.AI.",
      "href": "https://arxiv.org/abs/2607.15775"
    }
  ],
  "source": "arXiv cs.AI",
  "publishedAt": "2026-07-20",
  "expiryAt": "2026-08-19T00:00:00.000Z",
  "author": "Muntasir Tabasum, Al Zadid Sultan Bin Habib, Tanpia Tasnim, Md. Ekramul Islam, Md Younus Ahamed, Md Asif Bin Syed"
}