{
  "type": "news",
  "slug": "arxiv-cs-ai-oai-arxiv-org-2606-12808v4",
  "name": "SymQNet: Amortized Acquisition for Low-Latency Adaptive Hamiltonian Learning",
  "summary": "arXiv:2606.12808v4 Announce Type: replace-cross Abstract: Adaptive Hamiltonian learning is central to calibrating and characterizing quantum devices. In an adaptive controller, choosing the next ex...",
  "description": "arXiv:2606.12808v4 Announce Type: replace-cross Abstract: Adaptive Hamiltonian learning is central to calibrating and characterizing quantum devices. In an adaptive controller, choosing the next experiment is itself a computation. Bayesian design rules are recomputed after every posterior update, and that step can take seconds. Across hundreds of shots, those seconds become a significant wall-c...",
  "tags": [
    "news",
    "arxiv-cs-ai"
  ],
  "externalLinks": [
    {
      "label": "arXiv cs.AI",
      "href": "https://arxiv.org/abs/2606.12808"
    }
  ],
  "timeline": [
    {
      "date": "2026-07-24",
      "type": "milestone",
      "title": "Published",
      "description": "Posted by arXiv cs.AI.",
      "href": "https://arxiv.org/abs/2606.12808"
    }
  ],
  "source": "arXiv cs.AI",
  "publishedAt": "2026-07-24",
  "expiryAt": "2026-08-23T00:00:00.000Z",
  "author": "Yash Vardhan Tomar, Dheeraj Peddireddy"
}