{
  "type": "news",
  "slug": "arxiv-cs-ai-oai-arxiv-org-2607-19364v1",
  "name": "Statistically Grounded Sparse-Feature Interventions for Activation-Space Control in Large Language Models",
  "summary": "arXiv:2607.19364v1 Announce Type: new Abstract: Activation steering offers a lightweight alternative to fine-tuning for behavioral control of large language models, but SAE-based steering methods o...",
  "description": "arXiv:2607.19364v1 Announce Type: new Abstract: Activation steering offers a lightweight alternative to fine-tuning for behavioral control of large language models, but SAE-based steering methods often rely on learned steering objectives or single-criterion feature selection. We introduce a transparent SAE-feature steering pipeline that first applies a six-condition reliability filter, then ran...",
  "tags": [
    "news",
    "arxiv-cs-ai"
  ],
  "externalLinks": [
    {
      "label": "arXiv cs.AI",
      "href": "https://arxiv.org/abs/2607.19364"
    }
  ],
  "timeline": [
    {
      "date": "2026-07-23",
      "type": "milestone",
      "title": "Published",
      "description": "Posted by arXiv cs.AI.",
      "href": "https://arxiv.org/abs/2607.19364"
    }
  ],
  "source": "arXiv cs.AI",
  "publishedAt": "2026-07-23",
  "expiryAt": "2026-08-22T00:00:00.000Z",
  "author": "Oshayer Siddique, J. M Areeb Uzair Alam, Md Jobayer Rahman Rafy, Syed Rifat Raiyan, Hasan Mahmud, Md Kamrul Hasan"
}