{
  "type": "news",
  "slug": "arxiv-cs-ai-oai-arxiv-org-2607-13073v1",
  "name": "Probabilistic Extension of Neuro-Symbolic AGI Robots based on Belnap's Typed Intensional FOL",
  "summary": "arXiv:2607.13073v1 Announce Type: new Abstract: Neuro-symbolic AI based on $IFOL_B$ is a way to combine neural learning and symbolic reasoning to overcome limitations of purely neural systems (like...",
  "description": "arXiv:2607.13073v1 Announce Type: new Abstract: Neuro-symbolic AI based on $IFOL_B$ is a way to combine neural learning and symbolic reasoning to overcome limitations of purely neural systems (like lack of interpretability and logical structure) with formal logical machinery for self-reference. In this paper we expand the cognitive power of $IFOL_B$ by using the probability computation for the...",
  "tags": [
    "news",
    "arxiv-cs-ai"
  ],
  "externalLinks": [
    {
      "label": "arXiv cs.AI",
      "href": "https://arxiv.org/abs/2607.13073"
    }
  ],
  "timeline": [
    {
      "date": "2026-07-16",
      "type": "milestone",
      "title": "Published",
      "description": "Posted by arXiv cs.AI.",
      "href": "https://arxiv.org/abs/2607.13073"
    }
  ],
  "source": "arXiv cs.AI",
  "publishedAt": "2026-07-16",
  "expiryAt": "2026-08-15T00:00:00.000Z",
  "author": "Zoran Majkic"
}