{
  "type": "news",
  "slug": "arxiv-cs-ai-oai-arxiv-org-2607-13643v1",
  "name": "Consensus as Privileged Context for Label-Free Self-Distillation",
  "summary": "arXiv:2607.13643v1 Announce Type: cross Abstract: Sampling multiple solutions and returning the majority answer is among the most reliable ways to improve the reasoning accuracy of large language m...",
  "description": "arXiv:2607.13643v1 Announce Type: cross Abstract: Sampling multiple solutions and returning the majority answer is among the most reliable ways to improve the reasoning accuracy of large language models without labels, and a growing family of methods converts this consensus signal into training supervision. However, existing approaches use consensus only in restricted forms: as a filter that se...",
  "tags": [
    "news",
    "arxiv-cs-ai"
  ],
  "externalLinks": [
    {
      "label": "arXiv cs.AI",
      "href": "https://arxiv.org/abs/2607.13643"
    }
  ],
  "timeline": [
    {
      "date": "2026-07-16",
      "type": "milestone",
      "title": "Published",
      "description": "Posted by arXiv cs.AI.",
      "href": "https://arxiv.org/abs/2607.13643"
    }
  ],
  "source": "arXiv cs.AI",
  "publishedAt": "2026-07-16",
  "expiryAt": "2026-08-15T00:00:00.000Z",
  "author": "John Gkountouras, Josip Juki\\'c, Ivan Titov"
}