{
  "type": "news",
  "slug": "arxiv-cs-ai-oai-arxiv-org-2607-13716v1",
  "name": "CAVA: Canonical Action Verification and Attestation for Runtime Governance of Agentic AI Systems",
  "summary": "arXiv:2607.13716v1 Announce Type: new Abstract: Agentic AI systems increasingly act through heterogeneous runtimes: local coding hooks, SDK tools, browser automation, managed-agent traces, API gate...",
  "description": "arXiv:2607.13716v1 Announce Type: new Abstract: Agentic AI systems increasingly act through heterogeneous runtimes: local coding hooks, SDK tools, browser automation, managed-agent traces, API gateways, and workflow engines. A single operational act such as publishing code, changing identity state, moving money, or exporting data may therefore be represented by many incompatible runtime records...",
  "tags": [
    "news",
    "arxiv-cs-ai"
  ],
  "externalLinks": [
    {
      "label": "arXiv cs.AI",
      "href": "https://arxiv.org/abs/2607.13716"
    }
  ],
  "timeline": [
    {
      "date": "2026-07-16",
      "type": "milestone",
      "title": "Published",
      "description": "Posted by arXiv cs.AI.",
      "href": "https://arxiv.org/abs/2607.13716"
    }
  ],
  "source": "arXiv cs.AI",
  "publishedAt": "2026-07-16",
  "expiryAt": "2026-08-15T00:00:00.000Z",
  "author": "Zexun Wang"
}