{
  "type": "news",
  "slug": "arxiv-cs-ai-oai-arxiv-org-2603-16307v3",
  "name": "NeSy-Route: A Neuro-Symbolic Benchmark for Constrained Route Planning in Remote Sensing",
  "summary": "arXiv:2603.16307v3 Announce Type: replace Abstract: Remote sensing underpins crucial applications such as disaster relief and ecological field surveys, where systems must understand complex scenes...",
  "description": "arXiv:2603.16307v3 Announce Type: replace Abstract: Remote sensing underpins crucial applications such as disaster relief and ecological field surveys, where systems must understand complex scenes and constraints and make reliable decisions. Current remote-sensing benchmarks mainly focus on evaluating perception and reasoning capabilities of multimodal large language models (MLLMs). They fail t...",
  "tags": [
    "news",
    "arxiv-cs-ai"
  ],
  "externalLinks": [
    {
      "label": "arXiv cs.AI",
      "href": "https://arxiv.org/abs/2603.16307"
    }
  ],
  "timeline": [
    {
      "date": "2026-07-16",
      "type": "milestone",
      "title": "Published",
      "description": "Posted by arXiv cs.AI.",
      "href": "https://arxiv.org/abs/2603.16307"
    }
  ],
  "source": "arXiv cs.AI",
  "publishedAt": "2026-07-16",
  "expiryAt": "2026-08-15T00:00:00.000Z",
  "author": "Ming Yang, Zhi Zhou, Shi-Yu Tian, Kun-Yang Yu, Lan-Zhe Guo, Yu-Feng Li"
}