{
  "type": "news",
  "slug": "arxiv-cs-ai-oai-arxiv-org-2607-16448v1",
  "name": "Retrieval is Enough: Training-Free Interpretability with a Tool-Using Agent",
  "summary": "arXiv:2607.16448v1 Announce Type: cross Abstract: Interpretability methods for neural network activations span a wide cost spectrum, from cheap, training-free techniques (such as linear probes, PCA...",
  "description": "arXiv:2607.16448v1 Announce Type: cross Abstract: Interpretability methods for neural network activations span a wide cost spectrum, from cheap, training-free techniques (such as linear probes, PCA, SVD) to more expensive training-based ones (such as SAEs and activation oracles). Training-based methods are typically more powerful, in part because they leverage large activation datasets during t...",
  "tags": [
    "news",
    "arxiv-cs-ai"
  ],
  "externalLinks": [
    {
      "label": "arXiv cs.AI",
      "href": "https://arxiv.org/abs/2607.16448"
    }
  ],
  "timeline": [
    {
      "date": "2026-07-21",
      "type": "milestone",
      "title": "Published",
      "description": "Posted by arXiv cs.AI.",
      "href": "https://arxiv.org/abs/2607.16448"
    }
  ],
  "source": "arXiv cs.AI",
  "publishedAt": "2026-07-21",
  "expiryAt": "2026-08-20T00:00:00.000Z",
  "author": "Sriram Balasubramanian, Soheil Feizi"
}