{
  "type": "news",
  "slug": "arxiv-cs-ai-oai-arxiv-org-2607-16591v1",
  "name": "Learning from World Feedback: Why Model Uncertainty Fails as a Risk Signal in Model-Based RL",
  "summary": "arXiv:2607.16591v1 Announce Type: cross Abstract: The RLxF programme argues that learning signals should come from world feedback rather than from internal model proxies. We instantiate this positi...",
  "description": "arXiv:2607.16591v1 Announce Type: cross Abstract: The RLxF programme argues that learning signals should come from world feedback rather than from internal model proxies. We instantiate this position in safe model-based control and distil it into three concrete design principles. Empirically, across four world-model architectures spanning a 2x MSE range, MPC planning is statistically equivalent...",
  "tags": [
    "news",
    "arxiv-cs-ai"
  ],
  "externalLinks": [
    {
      "label": "arXiv cs.AI",
      "href": "https://arxiv.org/abs/2607.16591"
    }
  ],
  "timeline": [
    {
      "date": "2026-07-21",
      "type": "milestone",
      "title": "Published",
      "description": "Posted by arXiv cs.AI.",
      "href": "https://arxiv.org/abs/2607.16591"
    }
  ],
  "source": "arXiv cs.AI",
  "publishedAt": "2026-07-21",
  "expiryAt": "2026-08-20T00:00:00.000Z",
  "author": "Zhaohui Wang"
}