{
  "type": "news",
  "slug": "mit-news-ai-https-news-mit-edu-2026-mit-initiative-for-new-manufacturing-builds-momentum-0616",
  "name": "MIT’s Initiative for New Manufacturing builds momentum",
  "summary": "In its first year, INM has worked across research, workforce development, and industry engagement to help accelerate new manufacturing technologies and their real-world deployment.",
  "description": "In its first year, INM has worked across research, workforce development, and industry engagement to help accelerate new manufacturing technologies and their real-world deployment.",
  "tags": [
    "news",
    "mit-news-ai"
  ],
  "externalLinks": [
    {
      "label": "MIT News",
      "href": "https://news.mit.edu/2026/mit-initiative-for-new-manufacturing-builds-momentum-0616"
    }
  ],
  "timeline": [
    {
      "date": "2026-06-16",
      "type": "milestone",
      "title": "Published",
      "description": "Posted by MIT News.",
      "href": "https://news.mit.edu/2026/mit-initiative-for-new-manufacturing-builds-momentum-0616"
    }
  ],
  "source": "MIT News",
  "publishedAt": "2026-06-16",
  "expiryAt": "2026-07-16T00:00:00.000Z",
  "author": "Julie Diop | Initiative for New Manufacturing"
}