{
  "type": "news",
  "slug": "arxiv-cs-ai-oai-arxiv-org-2607-09760v2",
  "name": "Physics-Informed Structure Anchoring With Capture-Aware Prototype Calibration for Cross-Environment RF Fingerprinting",
  "summary": "arXiv:2607.09760v2 Announce Type: replace-cross Abstract: Radio frequency fingerprint identification (RFFI) exploits transmitter-specific hardware imperfections as physicallayer identity cues for I...",
  "description": "arXiv:2607.09760v2 Announce Type: replace-cross Abstract: Radio frequency fingerprint identification (RFFI) exploits transmitter-specific hardware imperfections as physicallayer identity cues for Internet of Things (IoT) devices, but deep models often degrade across acquisition environments. In multi-antenna reception, antenna topology and frequencyoffset dynamics structure receiver observation...",
  "tags": [
    "news",
    "arxiv-cs-ai"
  ],
  "externalLinks": [
    {
      "label": "arXiv cs.AI",
      "href": "https://arxiv.org/abs/2607.09760"
    }
  ],
  "timeline": [
    {
      "date": "2026-07-15",
      "type": "milestone",
      "title": "Published",
      "description": "Posted by arXiv cs.AI.",
      "href": "https://arxiv.org/abs/2607.09760"
    }
  ],
  "source": "arXiv cs.AI",
  "publishedAt": "2026-07-15",
  "expiryAt": "2026-08-14T00:00:00.000Z",
  "author": "Fengchong Yao, Jianbing Li, Qing Liu, Qikun Liu, Kefeng Song, Haitao Li, Song Wang"
}