{
  "type": "news",
  "slug": "arxiv-cs-ai-oai-arxiv-org-2607-12570v1",
  "name": "Deep Learning-based Surrogate Modelling of the LOD Method for Multiscale Problems",
  "summary": "arXiv:2607.12570v1 Announce Type: cross Abstract: Multiscale problems are notoriously difficult to tackle using traditional numerical methods, as accurately resolving fine-scale features often requ...",
  "description": "arXiv:2607.12570v1 Announce Type: cross Abstract: Multiscale problems are notoriously difficult to tackle using traditional numerical methods, as accurately resolving fine-scale features often requires prohibitively fine discretizations. This challenge is particularly pronounced in applications such as materials science, fluid dynamics, climate systems, chemical processes, and complex networks....",
  "tags": [
    "news",
    "arxiv-cs-ai"
  ],
  "externalLinks": [
    {
      "label": "arXiv cs.AI",
      "href": "https://arxiv.org/abs/2607.12570"
    }
  ],
  "timeline": [
    {
      "date": "2026-07-15",
      "type": "milestone",
      "title": "Published",
      "description": "Posted by arXiv cs.AI.",
      "href": "https://arxiv.org/abs/2607.12570"
    }
  ],
  "source": "arXiv cs.AI",
  "publishedAt": "2026-07-15",
  "expiryAt": "2026-08-14T00:00:00.000Z",
  "author": "Marc Haltmayer, Jaemin Seo, Yuseung Lee, Sungyeop Lee, Jaehoon Jeong, Jae Yong Lee"
}