{
  "source": "rss",
  "sourceId": "arxiv-cs-ai:oai:arXiv.org:2607.13108v1",
  "fetchedAt": "2026-07-16T05:17:56.085Z",
  "data": {
    "guid": "arxiv-cs-ai:oai:arXiv.org:2607.13108v1",
    "title": "STKAN: Kolmogorov-Arnold Networks for Spatio-Temporal Forecasting",
    "link": "https://arxiv.org/abs/2607.13108",
    "description": "arXiv:2607.13108v1 Announce Type: cross Abstract: Real-world traffic data exhibit heterogeneous spatial correlations and nonlinear temporal dynamics, posing substantial challenges for accurate spatio-temporal forecasting. Existing approaches have developed increasingly sophisticated graph, attention, and decomposition architectures, while the influence of the underlying nonlinear function approximator has received comparatively less attention. In this work, we propose STKAN, a spatio-temporal forecasting architecture that introduces Taylor-polynomial Kolmogorov--Arnold Network modules into spatial and temporal token mixing. STKAN first constructs high-level spatial representations through a learnable soft node-group assignment mechanism, applies group-wise spatial mixing, and subsequently models temporal dependencies over the compressed sequence. Spatial and temporal self-attention layers are further employed to capture long-range interactions. Experiments on five traffic forecasting benchmarks show that STKAN achieves competitive performance and performs better than the evaluated MLP-based variant in the tested settings. These results suggest that the design of nonlinear function approximators can serve as a useful complement to architectural design in spatio-temporal forecasting.",
    "publishedAt": "2026-07-16",
    "author": "Sicong Lai, Yuehong Hu, Siru Zhong, Si Qiao, Yuxuan Liang, Guangyin Jin",
    "feedId": "arxiv-cs-ai",
    "source": "arXiv cs.AI"
  },
  "extra": {
    "feedId": "arxiv-cs-ai",
    "source": "arXiv cs.AI"
  }
}