{
  "source": "rss",
  "sourceId": "arxiv-cs-ai:oai:arXiv.org:2607.10357v1",
  "fetchedAt": "2026-07-14T05:07:36.736Z",
  "data": {
    "guid": "arxiv-cs-ai:oai:arXiv.org:2607.10357v1",
    "title": "GRC-ProbNet: Uncertainty-aware Feature Extraction for Cardiovascular Disease Classification",
    "link": "https://arxiv.org/abs/2607.10357",
    "description": "arXiv:2607.10357v1 Announce Type: cross Abstract: The automatic detection and classification of cardiovascular disease (CVD) from computed tomography (CT) images plays an important role in clinical practice. Recently, a hybrid pipeline (GRC-Net) for CVD classification was proposed, which leverages a deep-learning-based segmentation and registration method to extract radiomic and geometric features. However, GRC-Net relies on a deterministic segmentation mask, without considering the inherent ambiguity associated with cardiac anatomy. In this paper, we propose GRC-ProbNet, which takes advantage of a deep ensemble to produce multiple segmentation masks for a given input. From these masks, we extract multiple uncertainty features. We analyze these uncertainty features for both their correlation with segmentation error and their propagation effects on downstream CVD classification performance. Our experiments on the publicly available MM-WHS and ASOCA datasets show that the uncertainty measure that best reflects segmentation quality is not necessarily the one that provides the strongest signal for downstream CVD classification. Overall, our results demonstrate that GRC-ProbNet utilizing uncertainty features substantially improves CVD classification AUROC (92.92\\) compared to the baseline GRC-Net model (91.25%). Our code is publicly available: https://github.com/biomedia-mira/GRC-ProbNet.",
    "publishedAt": "2026-07-14",
    "author": "Yash Shah, Omar Todd, Philipp Seeb\\\"ock, Georg Langs, Ben Glocker, Raghav Mehta",
    "feedId": "arxiv-cs-ai",
    "source": "arXiv cs.AI"
  },
  "extra": {
    "feedId": "arxiv-cs-ai",
    "source": "arXiv cs.AI"
  }
}