{
  "source": "rss",
  "sourceId": "arxiv-cs-ai:oai:arXiv.org:2607.16366v1",
  "fetchedAt": "2026-07-21T05:28:09.406Z",
  "data": {
    "guid": "arxiv-cs-ai:oai:arXiv.org:2607.16366v1",
    "title": "PRISM: Multimodal Terrain Mapping for Rover Navigation in Unstructured Environments",
    "link": "https://arxiv.org/abs/2607.16366",
    "description": "arXiv:2607.16366v1 Announce Type: cross Abstract: Robotic navigation in unstructured environments requires robust situational awareness to safely traverse hazards such as steep slopes and rocky terrain. To address this challenge, perception systems increasingly rely on multimodal sensor fusion. Specifically, integrating thermal imagery with standard optical and depth sensors enhances terrain differentiation, directly improving the reliability of mapping algorithms. This paper presents PRISM, a multimodal perception system for terrain mapping in unstructured settings. PRISM leverages a custom sensor suite to capture aligned RGB, depth, and thermal (RGB-D-T) imagery. At its core is OmniUnet, a novel vision transformer-based network specifically designed for multimodal semantic terrain segmentation. We validated the proposed system using two newly annotated datasets (BASEPROD and LAENTIEC) and demonstrate its real-world applicability through physical field experiments. Deployed on a resource-constrained embedded computer, PRISM efficiently generates traversability maps that directly enable autonomous navigation via a rover's Guidance, Navigation, and Control (GNC) subsystem.",
    "publishedAt": "2026-07-21",
    "author": "Raul Castilla-Arquillo, Carlos Perez-del-Pulgar, Levin Gerdes, Alfonso Garcia-Cerezo, Miguel A. Olivares-Mendez",
    "feedId": "arxiv-cs-ai",
    "source": "arXiv cs.AI"
  },
  "extra": {
    "feedId": "arxiv-cs-ai",
    "source": "arXiv cs.AI"
  }
}